{"name":"Sdd-gameshow-wiki","tagline":"A repo for the gameshow and a wiki","body":"# SDD GameShow and Wiki\r\nA place for the gameshow and a wiki\r\n![SDD logo](https://github.com/willyb321/SDD-GameShow-Wiki/blob/master/SDD.logo.png)\r\n***\r\nMembers:\r\n- William Blythe\r\n- Austin Brown\r\n- Ben Newton\r\n- Zac Williams\r\n- Oscar Rainford\r\n\r\n***\r\nThis project was/is being made for education purposes, and is being done as a group project.\r\n***\r\nSee the [wiki](https://github.com/willyb321/SDD-GameShow-Wiki/wiki) for that part of the project\r\n***\r\nSee the website (you're on it) for the trivia/quiz.\r\n\r\nThe website will be hosted with github pages, to avoid hosting costs.","google":"UA-55840909-5","note":"Don't delete this file! It's used internally to help with page regeneration."}